discord_dumper/__init__.py
discord_dumper/__main__.py
discord_dumper/cli.py
discord_dumper/core.py
discord_dumper/dumper.py
discord_dumper/py.typed
discord_dumper-0.0.1.dist-info/LICENSE
discord_dumper-0.0.1.dist-info/METADATA
discord_dumper-0.0.1.dist-info/WHEEL
discord_dumper-0.0.1.dist-info/entry_points.txt
discord_dumper-0.0.1.dist-info/RECORD
