Metadata-Version: 2.1
Name: discord-dumper
Version: 0.0.1
Summary: Retrieve all your discord information using a HAR file.
Home-page: https://github.com/Dashstrom/discord-dumper
License: MIT
Keywords: python
Author: Dashstrom
Author-email: dashstrom.pro@gmail.com
Maintainer: Dashstrom
Maintainer-email: dashstrom.pro@gmail.com
Requires-Python: >=3.8
Classifier: Development Status :: 3 - Alpha
Classifier: Environment :: Console
Classifier: Framework :: Pytest
Classifier: Framework :: Sphinx
Classifier: Framework :: tox
Classifier: Intended Audience :: Developers
Classifier: Intended Audience :: System Administrators
Classifier: License :: OSI Approved :: MIT License
Classifier: Natural Language :: English
Classifier: Operating System :: OS Independent
Classifier: Programming Language :: Python :: 3
Classifier: Programming Language :: Python :: 3.8
Classifier: Programming Language :: Python :: 3.9
Classifier: Programming Language :: Python :: 3.10
Classifier: Programming Language :: Python :: 3.11
Classifier: Programming Language :: Python :: 3.12
Classifier: Programming Language :: Python :: 3 :: Only
Classifier: Typing :: Typed
Provides-Extra: cov
Provides-Extra: docs
Provides-Extra: format
Provides-Extra: lint
Provides-Extra: tasks
Provides-Extra: test
Requires-Dist: commitizen (==3.25.0) ; extra == "tasks"
Requires-Dist: coverage[toml] (==7.5.0) ; extra == "cov"
Requires-Dist: mypy (==1.10.0) ; extra == "lint" or extra == "format"
Requires-Dist: orjson
Requires-Dist: poethepoet (==0.26.1) ; extra == "tasks"
Requires-Dist: pre-commit (==3.5.0) ; extra == "tasks"
Requires-Dist: pytest (==8.2.0) ; extra == "test" or extra == "cov" or extra == "lint" or extra == "format"
Requires-Dist: pytest-cov (==5.0.0) ; extra == "cov"
Requires-Dist: pytest-mock (==3.14.0) ; extra == "test" or extra == "cov" or extra == "lint" or extra == "format"
Requires-Dist: ruff (==0.4.3) ; extra == "lint" or extra == "format"
Requires-Dist: sphinx (==7.1.2) ; extra == "docs"
Requires-Dist: sphinx-rtd-theme (==2.0.0) ; extra == "docs"
Requires-Dist: sphinxcontrib-mermaid (==0.9.2) ; extra == "docs"
Requires-Dist: typing-extensions (>=4.8.0)
Project-URL: Documentation, https://dashstrom.github.io/discord-dumper
Project-URL: Repository, https://github.com/Dashstrom/discord-dumper
